anyd/__init__.py
anyd/core.py
anyd-0.4.1.dist-info/entry_points.txt
anyd-0.4.1.dist-info/WHEEL
anyd-0.4.1.dist-info/METADATA
anyd-0.4.1.dist-info/RECORD
