Metadata-Version: 2.1
Name: anyd
Version: 0.4.1
Summary: A small framework for building and using custom Unix daemons.
Home-page: https://github.com/anatolio-deb/anyd
License: BSD
Keywords: ipc,sockets,daemon
Author: Anatolio Nikiforidis
Author-email: nikiforova693@gmail.com
Requires-Python: >=3.8,<4.0
Classifier: Development Status :: 4 - Beta
Classifier: Environment :: Console
Classifier: Intended Audience :: Developers
Classifier: License :: OSI Approved :: MIT License
Classifier: License :: Other/Proprietary License
Classifier: Natural Language :: English
Classifier: Operating System :: POSIX :: Linux
Classifier: Programming Language :: Python :: 3
Classifier: Programming Language :: Python :: 3.8
Classifier: Programming Language :: Python :: 3.9
Classifier: Programming Language :: Python :: Implementation :: CPython
Classifier: Topic :: Software Development :: Libraries :: Application Frameworks
Classifier: Topic :: Software Development :: Libraries :: Python Modules
Project-URL: Repository, https://github.com/anatolio-deb/anyd
